orange_widget_base-4.27.0.dist-info/licenses/LICENSE
orangewidget/__init__.py
orangewidget/gui.py
orangewidget/io.py
orangewidget/settings.py
orangewidget/version.py
orangewidget/widget.py
orangewidget/i18n/English.json
orangewidget/i18n/Slovenian.json
orangewidget/icons/Dlg_arrow.png
orangewidget/icons/Dlg_clear.png
orangewidget/icons/Dlg_down3.png
orangewidget/icons/Dlg_enter.png
orangewidget/icons/Dlg_pan_hand.png
orangewidget/icons/Dlg_redo.png
orangewidget/icons/Dlg_send.png
orangewidget/icons/Dlg_sort.png
orangewidget/icons/Dlg_undo.png
orangewidget/icons/Dlg_up3.png
orangewidget/icons/Dlg_zoom.png
orangewidget/icons/Dlg_zoom_reset.png
orangewidget/icons/Dlg_zoom_selection.png
orangewidget/icons/Unknown.png
orangewidget/icons/chart.svg
orangewidget/icons/downgreenarrow.png
orangewidget/icons/error.png
orangewidget/icons/hamburger.svg
orangewidget/icons/help.svg
orangewidget/icons/information.png
orangewidget/icons/input-empty.svg
orangewidget/icons/input-partial.svg
orangewidget/icons/input.svg
orangewidget/icons/output-empty.svg
orangewidget/icons/output-partial.svg
orangewidget/icons/output.svg
orangewidget/icons/report.svg
orangewidget/icons/reset.svg
orangewidget/icons/upgreenarrow.png
orangewidget/icons/visual-settings.svg
orangewidget/icons/warning.png
orangewidget/report/__init__.py
orangewidget/report/index.html
orangewidget/report/owreport.py
orangewidget/report/report.py
orangewidget/report/icons/delete.svg
orangewidget/report/icons/scheme.svg
orangewidget/report/tests/__init__.py
orangewidget/report/tests/test_report.py
orangewidget/tests/__init__.py
orangewidget/tests/base.py
orangewidget/tests/test_context_handler.py
orangewidget/tests/test_control_getter.py
orangewidget/tests/test_gui.py
orangewidget/tests/test_io.py
orangewidget/tests/test_matplotlib_export.py
orangewidget/tests/test_setting_provider.py
orangewidget/tests/test_settings_handler.py
orangewidget/tests/test_test_base.py
orangewidget/tests/test_widget.py
orangewidget/tests/utils.py
orangewidget/utils/PDFExporter.py
orange_widget_base-4.27.0.dist-info/METADATA
orange_widget_base-4.27.0.dist-info/WHEEL
orange_widget_base-4.27.0.dist-info/top_level.txt
orange_widget_base-4.27.0.dist-info/RECORD
