Metadata-Version: 2.4
Name: orange-widget-base
Version: 4.27.0
Summary: Base Widget for Orange Canvas
Home-page: http://orange.biolab.si/
Author: Bioinformatics Laboratory, FRI UL
Author-email: info@biolab.si
License: GPLv3+
Keywords: workflow,widget
Classifier: Development Status :: 4 - Beta
Classifier: Environment :: X11 Applications :: Qt
Classifier: Environment :: Console
Classifier: Environment :: Plugins
Classifier: Programming Language :: Python
Classifier: License :: OSI Approved :: GNU General Public License v3 or later (GPLv3+)
Classifier: Operating System :: POSIX
Classifier: Operating System :: Microsoft :: Windows
Classifier: Topic :: Scientific/Engineering :: Artificial Intelligence
Classifier: Topic :: Scientific/Engineering :: Visualization
Classifier: Topic :: Software Development :: Libraries :: Python Modules
Classifier: Intended Audience :: Education
Classifier: Intended Audience :: Science/Research
Classifier: Intended Audience :: Developers
Requires-Python: >=3.10
License-File: LICENSE
Requires-Dist: matplotlib
Requires-Dist: pyqtgraph
Requires-Dist: AnyQt>=0.1.0
Requires-Dist: typing_extensions>=3.7.4.3
Requires-Dist: orange-canvas-core<0.3a,>=0.2a.dev0
Requires-Dist: appnope; sys_platform == "darwin"
Dynamic: author
Dynamic: author-email
Dynamic: classifier
Dynamic: description
Dynamic: description-content-type
Dynamic: home-page
Dynamic: keywords
Dynamic: license
Dynamic: license-file
Dynamic: requires-dist
Dynamic: requires-python
Dynamic: summary
